CryptoAiTools/__init__.py
CryptoAiTools/base.py
CryptoAiTools/bot_creator.py
CryptoAiTools/config.py
CryptoAiTools/helpers/base_helper.py
CryptoAiTools/helpers/basec_helper.py
CryptoAiTools-0.7.dist-info/METADATA
CryptoAiTools-0.7.dist-info/WHEEL
CryptoAiTools-0.7.dist-info/entry_points.txt
CryptoAiTools-0.7.dist-info/top_level.txt
CryptoAiTools-0.7.dist-info/RECORD
