Metadata-Version: 2.1
Name: CryptoAiTools
Version: 0.7
Summary: A Python toolkit to create and manage crypto trading bots
Author: CryptoAi
Requires-Dist: requests (==2.28.2)
Requires-Dist: Pillow (==9.5.0)
Requires-Dist: PyQt5 (==5.15.10)
Requires-Dist: pyzipper (==0.3.6)
